tensorflow_constrained_optimization/__init__.py
tensorflow_constrained_optimization/python/__init__.py
tensorflow_constrained_optimization/python/candidates.py
tensorflow_constrained_optimization/python/candidates_test.py
tensorflow_constrained_optimization/python/constrained_minimization_problem.py
tensorflow_constrained_optimization/python/graph_and_eager_test_case.py
tensorflow_constrained_optimization/python/rates/__init__.py
tensorflow_constrained_optimization/python/rates/basic_expression.py
tensorflow_constrained_optimization/python/rates/basic_expression_test.py
tensorflow_constrained_optimization/python/rates/binary_rates.py
tensorflow_constrained_optimization/python/rates/binary_rates_test.py
tensorflow_constrained_optimization/python/rates/constraint.py
tensorflow_constrained_optimization/python/rates/defaults.py
tensorflow_constrained_optimization/python/rates/deferred_tensor.py
tensorflow_constrained_optimization/python/rates/deferred_tensor_test.py
tensorflow_constrained_optimization/python/rates/expression.py
tensorflow_constrained_optimization/python/rates/expression_test.py
tensorflow_constrained_optimization/python/rates/helpers.py
tensorflow_constrained_optimization/python/rates/helpers_test.py
tensorflow_constrained_optimization/python/rates/loss.py
tensorflow_constrained_optimization/python/rates/loss_test.py
tensorflow_constrained_optimization/python/rates/operations.py
tensorflow_constrained_optimization/python/rates/operations_test.py
tensorflow_constrained_optimization/python/rates/predicate.py
tensorflow_constrained_optimization/python/rates/predicate_test.py
tensorflow_constrained_optimization/python/rates/rate_minimization_problem.py
tensorflow_constrained_optimization/python/rates/rate_minimization_problem_test.py
tensorflow_constrained_optimization/python/rates/subsettable_context.py
tensorflow_constrained_optimization/python/rates/subsettable_context_test.py
tensorflow_constrained_optimization/python/rates/term.py
tensorflow_constrained_optimization-0.2.dist-info/LICENSE
tensorflow_constrained_optimization-0.2.dist-info/METADATA
tensorflow_constrained_optimization-0.2.dist-info/WHEEL
tensorflow_constrained_optimization-0.2.dist-info/top_level.txt
tensorflow_constrained_optimization-0.2.dist-info/RECORD
