Metadata-Version: 2.1
Name: tensorflow-constrained-optimization
Version: 0.2
Summary: A library for performing constrained optimization in TensorFlow
Home-page: https://github.com/google-research/tensorflow_constrained_optimization
Author: Google Inc.
Author-email: no-reply@google.com
License: Apache 2.0
Keywords: tensorflow machine learning optimizer constraint rate
Platform: UNKNOWN
Classifier: Development Status :: 4 - Beta
Classifier: Intended Audience :: Developers
Classifier: Intended Audience :: Education
Classifier: Intended Audience :: Science/Research
Classifier: License :: OSI Approved :: Apache Software License
Classifier: Operating System :: OS Independent
Classifier: Programming Language :: Python
Classifier: Programming Language :: Python :: 2
Classifier: Programming Language :: Python :: 3
Classifier: Topic :: Scientific/Engineering
Classifier: Topic :: Scientific/Engineering :: Artificial Intelligence
Classifier: Topic :: Scientific/Engineering :: Mathematics
Classifier: Topic :: Software Development
Classifier: Topic :: Software Development :: Libraries
Classifier: Topic :: Software Development :: Libraries :: Python Modules
Requires-Dist: numpy
Requires-Dist: scipy
Requires-Dist: six
Requires-Dist: tensorflow (>=1.14)
